Metadata-Version: 2.1
Name: my-package-1201
Version: 1.0
Summary: 测试一下
Home-page: UNKNOWN
Author: kevin
Author-email: 18782269652@163.com
License: UNKNOWN
Platform: UNKNOWN
Classifier: Programming Language :: Python :: 3
Classifier: License :: OSI Approved :: MIT License
Classifier: Operating System :: OS Independent
Requires-Python: >=3
